aerostat/.DS_Store
aerostat/__init__.py
aerostat/__main__.py
aerostat/aws/Dockerfile
aerostat/aws/info.py
aerostat/aws/predict.py
aerostat/aws/serverless.yml
aerostat/cli.py
aerostat/core/__init__.py
aerostat/core/checks.py
aerostat/core/deployer.py
aerostat/core/installer.py
aerostat/core/loginer.py
aerostat/core/utils.py
aerostat/static/index.html
aerostat/static/python/lib/python3.9/site-packages/attachment_server/__init__.py
aerostat/static/python/lib/python3.9/site-packages/attachment_server/excel/__init__.py
aerostat/static/python/lib/python3.9/site-packages/attachment_server/excel/excel.py
aerostat/static/python/lib/python3.9/site-packages/attachment_server/excel/template.xlsm
aerostat/static/python/lib/python3.9/site-packages/attachment_server/server.py
aerostat/static/python/lib/python3.9/site-packages/attachment_server/utils.py
aerostat_launcher-0.0.9.dist-info/LICENSE
aerostat_launcher-0.0.9.dist-info/WHEEL
aerostat_launcher-0.0.9.dist-info/entry_points.txt
aerostat_launcher-0.0.9.dist-info/METADATA
aerostat_launcher-0.0.9.dist-info/RECORD
