Metadata-Version: 2.1
Name: aerostat-launcher
Version: 0.0.9
Summary: A simple CLI tool to deploy your Machine Learning models to cloud, with public API and connection templates ready to go.
Home-page: https://github.com/vinceyyy/Aerostat
License: GPL-3.0
Keywords: machine learning deployment,cloud,api
Author: Vincent Yan
Author-email: vincent.yan@blend360.com
Requires-Python: >=3.10,<4.0
Classifier: License :: OSI Approved :: GNU General Public License v3 (GPLv3)
Classifier: Programming Language :: Python :: 3
Classifier: Programming Language :: Python :: 3.10
Classifier: Programming Language :: Python :: 3.11
Requires-Dist: jinja2 (>=3.1.2,<4.0.0)
Requires-Dist: questionary (>=1.10.0,<2.0.0)
Requires-Dist: typer[all] (>=0.7.0,<0.8.0)
Project-URL: Repository, https://github.com/vinceyyy/Aerostat
